{
  "$schema": "http://json-schema.org/draft-07/schema#",
  "type": "object",
  "properties": {
    "commandFormat": {
      "type": "string",
      "not": {
        "enum": [
          "application/cmd+json",
          "application/cmd+protobuf",
          "application/swe+json",
          "application/swe+text",
          "application/swe+csv",
          "application/swe+binary"
        ]
      }
    },
    "any": {
      "description": "Any other properties to describe schema"
    }
  },
  "required": [ "commandFormat" ]
}